LICENSE
MANIFEST.in
README.rst
setup.py
django_profilebase.egg-info/PKG-INFO
django_profilebase.egg-info/SOURCES.txt
django_profilebase.egg-info/dependency_links.txt
django_profilebase.egg-info/not-zip-safe
django_profilebase.egg-info/requires.txt
django_profilebase.egg-info/top_level.txt
profilebase/__init__.py
profilebase/context_processors.py
profilebase/forms.py
profilebase/middleware.py
profilebase/models.py
profilebase/utils.py