Metadata-Version: 1.0
Name: django-profilebase
Version: 0.2.3
Summary: Tools for building a custom Profile class with authentication
Home-page: https://github.com/aino/django-profilebase
Author: Mikko Hellsing
Author-email: mikko@aino.se
License: BSD
Platform: UNKNOWN
Classifier: Development Status :: 3 - Alpha
Classifier: Environment :: Web Environment
Classifier: Intended Audience :: Developers
Classifier: License :: OSI Approved :: BSD License
Classifier: Operating System :: OS Independent
Classifier: Programming Language :: Python
Classifier: Topic :: Internet :: WWW/HTTP :: Dynamic Content
Classifier: Framework :: Django
